develop/__init__.py
develop/application.py
develop/main.py
develop/manage.py
develop/core/__init__.py
develop/core/config.py
develop/core/jwt.py
develop/core/middleware.py
develop/core/security.py
develop/crud/__init__.py
develop/crud/token.py
develop/crud/user.py
develop/models/Post.py
develop/models/Token.py
develop/models/User.py
develop/models/__init__.py
develop/schemas/__init__.py
develop/schemas/token.py
develop/schemas/user.py
develop/utils/__init__.py
develop/utils/app_event_funcs.py
develop/utils/dependencies.py
develop/utils/security.py
permissions_system/PermissionsSystem.py
permissions_system/__init__.py
permissions_system/constants.py
permissions_system/models.py
permissions_system-0.2.3.dist-info/LICENSE
permissions_system-0.2.3.dist-info/METADATA
permissions_system-0.2.3.dist-info/WHEEL
permissions_system-0.2.3.dist-info/top_level.txt
permissions_system-0.2.3.dist-info/RECORD
