Metadata-Version: 2.1
Name: permissions-system
Version: 0.2.3
Summary: Alternative to admin utilities for more autonomy, targeted towards FastAPI.
Home-page: https://github.com/zero-shubham/permissions_system
Author: Shubham Biswas
Author-email: shubhambiswas.zero@gmail.com
License: MIT
Platform: UNKNOWN
Classifier: License :: OSI Approved :: MIT License
Classifier: Programming Language :: Python :: 3
Classifier: Programming Language :: Python :: 3.8
Requires-Dist: sqlalchemy (==1.3.20)
Requires-Dist: pydantic (==1.6.1)
